PyPtt/PTT.py
PyPtt/__init__.py
PyPtt/_api_bucket.py
PyPtt/_api_call_status.py
PyPtt/_api_change_pw.py
PyPtt/_api_comment.py
PyPtt/_api_del_post.py
PyPtt/_api_get_board_info.py
PyPtt/_api_get_board_list.py
PyPtt/_api_get_bottom_post_list.py
PyPtt/_api_get_favourite_board.py
PyPtt/_api_get_newest_index.py
PyPtt/_api_get_post.py
PyPtt/_api_get_post_index.py
PyPtt/_api_get_post_list.py
PyPtt/_api_get_time.py
PyPtt/_api_get_user.py
PyPtt/_api_give_money.py
PyPtt/_api_has_new_mail.py
PyPtt/_api_loginout.py
PyPtt/_api_mail.py
PyPtt/_api_mark_post.py
PyPtt/_api_post.py
PyPtt/_api_reply_post.py
PyPtt/_api_search_user.py
PyPtt/_api_set_board_title.py
PyPtt/_api_util.py
PyPtt/api_server.py
PyPtt/check_value.py
PyPtt/command.py
PyPtt/config.py
PyPtt/connect_core.py
PyPtt/data_type.py
PyPtt/exceptions.py
PyPtt/i18n.py
PyPtt/lang_en_US.py
PyPtt/lang_zh_TW.py
PyPtt/lib_util.py
PyPtt/log.py
PyPtt/screens.py
PyPtt/service.py
PyPtt/ssl_config.py
pyptt-2.0.2.dist-info/licenses/LICENSE
pyptt-2.0.2.dist-info/METADATA
pyptt-2.0.2.dist-info/WHEEL
pyptt-2.0.2.dist-info/top_level.txt
pyptt-2.0.2.dist-info/RECORD
