Metadata-Version: 2.4
Name: PyPtt
Version: 2.0.2
Summary: PyPtt github: https://github.com/PyPtt/PyPtt
Author-email: CodingMan <pttcodingman@gmail.com>
License: GNU Lesser General Public License v3 (LGPLv3)
Project-URL: Homepage, https://pyptt.cc/
Project-URL: Repository, https://github.com/PyPtt/PyPtt
Keywords: PTT,crawler,bot,library,websockets
Classifier: Development Status :: 5 - Production/Stable
Classifier: Operating System :: OS Independent
Classifier: Intended Audience :: Developers
Classifier: Topic :: Communications :: BBS
Classifier: Topic :: Software Development :: Libraries :: Python Modules
Classifier: Topic :: Internet
Classifier: License :: OSI Approved :: GNU Lesser General Public License v3 (LGPLv3)
Classifier: Programming Language :: Python :: 3.11
Classifier: Programming Language :: Python :: 3.12
Classifier: Programming Language :: Python :: 3.13
Classifier: Programming Language :: Python :: 3.14
Classifier: Programming Language :: Python :: 3 :: Only
Classifier: Programming Language :: Python :: 3
Classifier: Natural Language :: Chinese (Traditional)
Classifier: Natural Language :: English
Requires-Python: >=3.11
License-File: LICENSE
Requires-Dist: progressbar2
Requires-Dist: websockets==12.0
Requires-Dist: uao
Requires-Dist: requests==2.32.4
Requires-Dist: AutoStrEnum
Requires-Dist: PyYAML
Provides-Extra: api
Requires-Dist: fastapi; extra == "api"
Requires-Dist: uvicorn[standard]; extra == "api"
Provides-Extra: dev
Requires-Dist: pytest; extra == "dev"
Requires-Dist: python-dotenv; extra == "dev"
Requires-Dist: flake8; extra == "dev"
Requires-Dist: sphinx; extra == "dev"
Requires-Dist: sphinx-copybutton; extra == "dev"
Requires-Dist: pygments==2.15.0; extra == "dev"
Requires-Dist: Furo; extra == "dev"
Requires-Dist: sphinx-sitemap; extra == "dev"
Dynamic: license-file
